pydeployment/__init__.py
pydeployment/__main__.py
pydeployment/arg_parser.py
pydeployment/build.py
pydeployment/build_config.py
pydeployment/build_linux.py
pydeployment/build_macos.py
pydeployment/build_windows.py
pydeployment/logger.py
pydeployment/linux/default.png
pydeployment/linux/license_appimagekit.txt
pydeployment/linux/appimagetool/appimagetool-aarch64.AppImage
pydeployment/linux/appimagetool/appimagetool-armhf.AppImage
pydeployment/linux/appimagetool/appimagetool-i686.AppImage
pydeployment/linux/appimagetool/appimagetool-x86_64.AppImage
pydeployment/linux/appimagetool/runtime-aarch64
pydeployment/linux/appimagetool/runtime-armhf
pydeployment/linux/appimagetool/runtime-i686
pydeployment/linux/appimagetool/runtime-x86_64
pydeployment/macos/default.icns
pydeployment/macos/entitlements.plist
pydeployment/windows/build.nsi
pydeployment/windows/default.ico
pydeployment/windows/license_pynsist.txt
pydeployment/windows/NSISPortable/NSISPortable.exe
pydeployment/windows/NSISPortable/help.html
pydeployment/windows/NSISPortable/App/Readme.txt
pydeployment/windows/NSISPortable/App/AppInfo/appicon.ico
pydeployment/windows/NSISPortable/App/AppInfo/appicon_128.png
pydeployment/windows/NSISPortable/App/AppInfo/appicon_16.png
pydeployment/windows/NSISPortable/App/AppInfo/appicon_256.png
pydeployment/windows/NSISPortable/App/AppInfo/appicon_32.png
pydeployment/windows/NSISPortable/App/AppInfo/appicon_75.png
pydeployment/windows/NSISPortable/App/AppInfo/appinfo.ini
pydeployment/windows/NSISPortable/App/AppInfo/installer.ini
pydeployment/windows/NSISPortable/App/AppInfo/pac_installer_log.ini
pydeployment/windows/NSISPortable/App/AppInfo/Launcher/Custom.nsh
pydeployment/windows/NSISPortable/App/AppInfo/Launcher/NSISPortable.ini
pydeployment/windows/NSISPortable/App/DefaultData/settings/nsisconf.nsh
pydeployment/windows/NSISPortable/App/NSIS/COPYING
pydeployment/windows/NSISPortable/App/NSIS/NSIS.chm
pydeployment/windows/NSISPortable/App/NSIS/NSIS.exe
pydeployment-1.3.11.dist-info/licenses/LICENSE
pydeployment-1.3.11.dist-info/METADATA
pydeployment-1.3.11.dist-info/WHEEL
pydeployment-1.3.11.dist-info/entry_points.txt
pydeployment-1.3.11.dist-info/top_level.txt
pydeployment-1.3.11.dist-info/RECORD
