Metadata-Version: 2.4
Name: pydeployment
Version: 1.3.11
Summary: Deploy Python projects with ease
Author-email: Zev Lee <60147316+zevlee@users.noreply.github.com>
Project-URL: Homepage, https://pydeployment.github.io
Project-URL: Bug Tracker, https://github.com/pydeployment/pydeployment/issues
Classifier: Programming Language :: Python :: 3
Classifier: License :: OSI Approved :: MIT License
Classifier: Operating System :: OS Independent
Requires-Python: >=3.10
License-File: LICENSE
Requires-Dist: python-dotenv==1.2.1
Dynamic: license-file
